[{"brand":"La Redoute Marie-Thérèse","name":"La porte des secrets","description":"Cela fait plus d’un demi siècle qu’une porte du fort est verrouillée, la clé mystérieuse a été retrouvée il y a quelques jours par hasard. Nous avons fait des recherches sur ce qui se trouve derrière cette porte dans les différents journaux des officiers de l’époque... En 1965, des rumeurs parlent d’une pièce hantée, de bruits étranges, d’une curieuse disparition.","snooping":null,"handling":null,"thinking":null,"rating":null,"userRating":null,"thumbnail":"https://escapegame.imgix.net/wp-content/uploads/2010/07/visite-des-souterrains-redoute-marie-therese-1.jpg","domain":"https://www.escapegame.fr/avrieux/redoute-marie-therese/la-porte-des-secrets/","roomSpecs":[{"Thème":"Horreur | Paranormal"},{"Nombre de joueurs":"2 à 6 joueurs"}]}]